README.md
app.py
setup.py
XStep_Service.egg-info/PKG-INFO
XStep_Service.egg-info/SOURCES.txt
XStep_Service.egg-info/dependency_links.txt
XStep_Service.egg-info/not-zip-safe
XStep_Service.egg-info/top_level.txt