Metadata-Version: 2.1
Name: XStep-Service
Version: 0.1
Summary: The interface for controlling X-Step Hw over REST Api.
Home-page: http://github.com/storborg/funniest
Author: Markus Veijola, Jukka-Pekka Salminen
Author-email: markus_veijola@mentor.com
License: BSD
Platform: UNKNOWN
Classifier: Programming Language :: Python :: 3
Classifier: License :: OSI Approved :: MIT License
Classifier: Operating System :: OS Independent
Requires-Python: >=3.6
